py_openshowvar.py
py_openshowvar-1.1.7.dist-info/LICENSE
py_openshowvar-1.1.7.dist-info/METADATA
py_openshowvar-1.1.7.dist-info/WHEEL
py_openshowvar-1.1.7.dist-info/top_level.txt
py_openshowvar-1.1.7.dist-info/RECORD
